cc86/__init__.py
cc86/cc86.py
cc86/cli.py
cc86-0.1.1.dist-info/AUTHORS.rst
cc86-0.1.1.dist-info/LICENSE
cc86-0.1.1.dist-info/METADATA
cc86-0.1.1.dist-info/WHEEL
cc86-0.1.1.dist-info/entry_points.txt
cc86-0.1.1.dist-info/top_level.txt
cc86-0.1.1.dist-info/RECORD
