Metadata-Version: 2.1
Name: cc86
Version: 0.1.1
Summary: C Cross Compiler for DOS & early 80x86 CPUs.
Home-page: https://github.com/johnnystarr/cc86
Author: Johnny Starr
Author-email: johnnystarr@gmail.com
License: GNU General Public License v3
Keywords: cc86
Platform: UNKNOWN
Classifier: Development Status :: 2 - Pre-Alpha
Classifier: Intended Audience :: Developers
Classifier: License :: OSI Approved :: GNU General Public License v3 (GPLv3)
Classifier: Natural Language :: English
Classifier: Programming Language :: Python :: 3
Classifier: Programming Language :: Python :: 3.5
Classifier: Programming Language :: Python :: 3.6
Classifier: Programming Language :: Python :: 3.7
Classifier: Programming Language :: Python :: 3.8
Requires-Python: >=3.5
Requires-Dist: Click (>=7.0)
